<annotation>
	<folder>motorcly</folder>
	<filename>image16.jpg</filename>
	<path>C:\Users\user\Downloads\motorcly\image16.jpg</path>
	<source>
		<database>Unknown</database>
	</source>
	<size>
		<width>600</width>
		<height>436</height>
		<depth>3</depth>
	</size>
	<segmented>0</segmented>
	<object>
		<name>motorcycle</name>
		<pose>Unspecified</pose>
		<truncated>0</truncated>
		<difficult>0</difficult>
		<bndbox>
			<xmin>144</xmin>
			<ymin>196</ymin>
			<xmax>448</xmax>
			<ymax>400</ymax>
		</bndbox>
	</object>
	<object>
		<name>motorcycle</name>
		<pose>Unspecified</pose>
		<truncated>0</truncated>
		<difficult>0</difficult>
		<bndbox>
			<xmin>48</xmin>
			<ymin>114</ymin>
			<xmax>166</xmax>
			<ymax>193</ymax>
		</bndbox>
	</object>
	<object>
		<name>helmet</name>
		<pose>Unspecified</pose>
		<truncated>0</truncated>
		<difficult>0</difficult>
		<bndbox>
			<xmin>231</xmin>
			<ymin>112</ymin>
			<xmax>278</xmax>
			<ymax>167</ymax>
		</bndbox>
	</object>
	<object>
		<name>helmet</name>
		<pose>Unspecified</pose>
		<truncated>0</truncated>
		<difficult>0</difficult>
		<bndbox>
			<xmin>80</xmin>
			<ymin>74</ymin>
			<xmax>109</xmax>
			<ymax>96</ymax>
		</bndbox>
	</object>
</annotation>
